{"name": "ぼかろめどれー", "updated": "2026-07-23", "fullFetched": "2026-07-23", "totalFetched": 228, "videos": [{"id": "NSDehR-TQNs", "t": "【2024年】ボカロ人気曲メドレー【作業用BGM】", "v": 2092670, "d": 566.09, "len": 9157, "voca": true, "cov": false}, {"id": "G1avGuBpE9A", "t": "【2012年】年代別ボカロ人気曲メドレー", "v": 1868709, "d": 944.71, "len": 60, "voca": true, "cov": false}, {"id": "FTFHvE6MuPU", "t": "【テーマ別】病み可愛い！ボカロ人気曲メドレー【作業用BGM】", "v": 1348624, "d": 552.71, "len": 5472, "voca": true, "cov": false}, {"id": "TJX3u57KR4M", "t": "【音楽ジャンル別】エレクトロスイング系ボカロ人気曲メドレー【作業用BGM】", "v": 817099, "d": 544.71, "len": 8467, "voca": true, "cov": false}, {"id": "k_efCw826PY", "t": "【テーマ別】都会系！夜のドライブで聞きたいボカロ人気曲メドレー【作業用BGM】", "v": 637062, "d": 530.71, "len": 8254, "voca": true, "cov": false}, {"id": "mC2_TvoH6Dg", "t": "【MIMI】ボカロP別人気曲メドレー", "v": 588343, "d": 887.84, "len": 59, "voca": true, "cov": false}, {"id": "U4qz3bYvjFc", "t": "【2023年】年代別ボカロ人気曲メドレー Part.1", "v": 542691, "d": 917.84, "len": 60, "voca": true, "cov": false}, {"id": "uHoebYmgGDY", "t": "【2023年】年代別ボカロ人気曲メドレー Part.2", "v": 421364, "d": 915.84, "len": 60, "voca": true, "cov": false}, {"id": "46jMbGTeCM8", "t": "【2022年】ボカロ人気曲メドレー【作業用BGM】", "v": 417731, "d": 897.09, "len": 8474, "voca": true, "cov": false}, {"id": "DNUcuf1ZNqY", "t": "【2019年】年代別ボカロ人気曲メドレー", "v": 412756, "d": 927.71, "len": 60, "voca": true, "cov": false}, {"id": "IlDsSUJ3GBc", "t": "【2023年】ボカロ人気曲メドレー【作業用BGM】", "v": 398389, "d": 895.09, "len": 9369, "voca": true, "cov": false}, {"id": "aDaUlmnd-LQ", "t": "【煮ル果実】ボカロP別人気曲メドレー", "v": 391805, "d": 872.09, "len": 60, "voca": true, "cov": false}, {"id": "Cqx-ouV23yY", "t": "【2017年】年代別ボカロ人気曲メドレー", "v": 346425, "d": 931.09, "len": 60, "voca": true, "cov": false}, {"id": "xAiApTF7x1Y", "t": "【2024年】年代別ボカロ人気曲メドレー Part.3", "v": 293312, "d": 558.71, "len": 60, "voca": true, "cov": false}, {"id": "IVtw6pA30Y4", "t": "【Giga】ボカロP別人気曲メドレー", "v": 284630, "d": 896.84, "len": 60, "voca": true, "cov": false}, {"id": "vmj1DYyoCw4", "t": "【2020年】年代別ボカロ人気曲メドレー", "v": 282438, "d": 925.71, "len": 60, "voca": true, "cov": false}, {"id": "aamfEfW27m4", "t": "【2010年】ボカロ人気曲メドレー【作業用BGM】", "v": 267220, "d": 1053.59, "len": 5810, "voca": true, "cov": false}, {"id": "wUftDe3gxeM", "t": "【テーマ別】地雷系!?明るくて病み可愛いボカロ曲メドレー②", "v": 247969, "d": 611.71, "len": 60, "voca": true, "cov": false}, {"id": "2XAtBXg5e70", "t": "【Eve】ボカロP別人気曲メドレー", "v": 244298, "d": 903.84, "len": 61, "voca": true, "cov": false}, {"id": "Jsj0AcYm24U", "t": "【すりぃ】ボカロP別人気曲メドレー", "v": 241556, "d": 900.09, "len": 57, "voca": true, "cov": false}, {"id": "Jm0O4qncM-8", "t": "【2009年】ボカロ人気曲メドレー【作業用BGM】", "v": 230419, "d": 1054.59, "len": 4023, "voca": true, "cov": false}, {"id": "DJ14u5KVz88", "t": "【r-906】ボカロP別人気曲メドレー", "v": 225211, "d": 826.84, "len": 60, "voca": true, "cov": false}, {"id": "tW2I7zEUpls", "t": "【2018年】年代別ボカロ人気曲メドレー", "v": 223408, "d": 930.09, "len": 60, "voca": true, "cov": false}, {"id": "eVhep-xXB60", "t": "【2016年】年代別ボカロ人気曲メドレー Part.1", "v": 214920, "d": 935.09, "len": 55, "voca": true, "cov": false}, {"id": "RiET4iuwGi0", "t": "【ひとしずく×やま△】ボカロP別人気曲メドレー", "v": 214752, "d": 880.84, "len": 60, "voca": true, "cov": false}, {"id": "CiW-yA1Mcws", "t": "【2016年】年代別ボカロ人気曲メドレー Part.2", "v": 213792, "d": 934.09, "len": 58, "voca": true, "cov": false}, {"id": "pICOK_UgBIk", "t": "【wotaku】ボカロP別人気曲メドレー", "v": 209429, "d": 868.84, "len": 59, "voca": true, "cov": false}, {"id": "ezhrQIskifQ", "t": "【2021年】年代別ボカロ人気曲メドレー Part.2", "v": 208284, "d": 921.84, "len": 60, "voca": true, "cov": false}, {"id": "707aM1nT2o8", "t": "【八王子P】ボカロP別人気曲メドレー", "v": 204123, "d": 830.09, "len": 60, "voca": true, "cov": false}, {"id": "W4gW-xRGOmA", "t": "【2011年】年代別ボカロ人気曲メドレー", "v": 196824, "d": 946.71, "len": 60, "voca": true, "cov": false}, {"id": "lJGc_dvAZvU", "t": "【2010年】年代別ボカロ人気曲メドレー", "v": 190266, "d": 950.71, "len": 56, "voca": true, "cov": false}, {"id": "zcztabb4J2s", "t": "【sasakure.UK】ボカロP別人気曲メドレー", "v": 189040, "d": 875.84, "len": 60, "voca": true, "cov": false}, {"id": "mxgtbFLK_XQ", "t": "【2013年】年代別ボカロ人気曲メドレー", "v": 188749, "d": 942.71, "len": 59, "voca": true, "cov": false}, {"id": "ARsi2SIYjXo", "t": "【ジャンル別】エレクトロスウィングなボカロ曲メドレー③", "v": 186179, "d": 555.71, "len": 60, "voca": true, "cov": false}, {"id": "T1Qp5pe_50w", "t": "【2022年】年代別ボカロ人気曲メドレー", "v": 181228, "d": 919.84, "len": 60, "voca": true, "cov": false}, {"id": "DtcKX-G0KiM", "t": "【みきとP】ボカロP別人気曲メドレー", "v": 178372, "d": 866.84, "len": 60, "voca": true, "cov": false}, {"id": "q5j5aZ-Uw90", "t": "【cosMo@暴走P】ボカロP別人気曲メドレー", "v": 177952, "d": 893.09, "len": 60, "voca": true, "cov": false}, {"id": "ee5tvUD0Ecs", "t": "【じん(自然の敵P)】ボカロP別人気曲メドレー Part.1", "v": 176172, "d": 819.84, "len": 57, "voca": true, "cov": false}, {"id": "rHyQ1kPyzvk", "t": "【MARETU】ボカロP別人気曲メドレー Part.1", "v": 174193, "d": 845.84, "len": 60, "voca": true, "cov": false}, {"id": "9tAVzqMzh8g", "t": "【2013年】ボカロ人気曲メドレー【作業用BGM】", "v": 169563, "d": 911.09, "len": 8811, "voca": true, "cov": false}, {"id": "LMm-RH5riDU", "t": "【ryo】ボカロP別人気曲メドレー", "v": 168659, "d": 908.84, "len": 60, "voca": true, "cov": false}, {"id": "ZSz6yOM4jmU", "t": "【ピノキオピー】ボカロP別人気曲メドレー Part.1", "v": 167632, "d": 877.83, "len": 60, "voca": true, "cov": false}, {"id": "QsEeTziZCWg", "t": "【2012年】ボカロ人気曲メドレー【作業用BGM】", "v": 166897, "d": 1050.59, "len": 7122, "voca": true, "cov": false}, {"id": "iKeQgeLLw1Y", "t": "【かいりきベア】ボカロP別人気曲メドレー", "v": 166626, "d": 894.84, "len": 60, "voca": true, "cov": false}, {"id": "Mc789CG-xAA", "t": "【いよわ】ボカロP別人気曲メドレー", "v": 164191, "d": 873.84, "len": 60, "voca": true, "cov": false}, {"id": "yJxRQcU3d1s", "t": "【2021年】ボカロ人気曲メドレー【作業用BGM】", "v": 162640, "d": 898.09, "len": 8486, "voca": true, "cov": false}, {"id": "hQIOf7L1iJQ", "t": "【Neru】ボカロP別人気曲メドレー", "v": 162270, "d": 898.84, "len": 60, "voca": true, "cov": false}, {"id": "5sUr0CytLFU", "t": "【トーマ】ボカロP別人気曲メドレー", "v": 162131, "d": 811.84, "len": 60, "voca": true, "cov": false}, {"id": "4wT59bdGKtA", "t": "【テーマ別】都会系!?夜に聞きたいエモいボカロ曲メドレー②", "v": 157788, "d": 607.71, "len": 60, "voca": true, "cov": false}, {"id": "9AZGuuKb9JI", "t": "【稲葉曇】ボカロP別人気曲メドレー", "v": 155894, "d": 851.09, "len": 60, "voca": true, "cov": false}, {"id": "ZvOHJZ5B_Gg", "t": "【2021年】年代別ボカロ人気曲メドレー Part.1", "v": 154067, "d": 923.84, "len": 56, "voca": true, "cov": false}, {"id": "U0j8v3dUwuQ", "t": "【傘村トータ 】ボカロP別人気曲メドレー", "v": 150752, "d": 837.09, "len": 60, "voca": true, "cov": false}, {"id": "WzQ0Dc4huGA", "t": "【きくお】ボカロP別人気曲メドレー", "v": 150067, "d": 821.84, "len": 60, "voca": true, "cov": false}, {"id": "FRxeBq8LuVY", "t": "【n-buna】ボカロP別人気曲メドレー", "v": 149038, "d": 891.84, "len": 60, "voca": true, "cov": false}, {"id": "bkTR7aR_Vy4", "t": "【DECO*27】ボカロP別人気曲メドレー Part.1", "v": 146154, "d": 882.84, "len": 60, "voca": true, "cov": false}, {"id": "AsQk5uNSTn0", "t": "【Ayase】ボカロP別人気曲メドレー", "v": 144643, "d": 852.84, "len": 60, "voca": true, "cov": false}, {"id": "uX-FWNPh9NU", "t": "【まふまふ】ボカロP別人気曲メドレー", "v": 143886, "d": 770.84, "len": 60, "voca": true, "cov": false}, {"id": "ufX11M0ZojM", "t": "【2015年】年代別ボカロ人気曲メドレー", "v": 141704, "d": 937.71, "len": 60, "voca": true, "cov": false}, {"id": "PXC6EGfb4lY", "t": "【2016年】ボカロ人気曲メドレー【作業用BGM】", "v": 140423, "d": 903.09, "len": 8441, "voca": true, "cov": false}, {"id": "9K8H8uH4ZVE", "t": "【2014年】ボカロ人気曲メドレー【作業用BGM】", "v": 138494, "d": 905.09, "len": 6959, "voca": true, "cov": false}, {"id": "JoVIbwPmqt0", "t": "【syudou】ボカロP別人気曲メドレー", "v": 136773, "d": 879.09, "len": 60, "voca": true, "cov": false}, {"id": "C43UMK-ZKb8", "t": "【ぺぽよ】ボカロP別人気曲メドレー", "v": 135903, "d": 740.84, "len": 60, "voca": true, "cov": false}, {"id": "mTJFvhterZ8", "t": "【2011年】ボカロ人気曲メドレー【作業用BGM】", "v": 133718, "d": 1052.59, "len": 5457, "voca": true, "cov": false}, {"id": "SYkcdCDVmzs", "t": "【ハチ】ボカロP別人気曲メドレー", "v": 128533, "d": 901.84, "len": 60, "voca": true, "cov": false}, {"id": "HqC4Ny3RT-g", "t": "【ナユタン星人】ボカロP別人気曲メドレー", "v": 125006, "d": 907.84, "len": 59, "voca": true, "cov": false}, {"id": "tjJpAr6JCG8", "t": "【ナナホシ管弦楽団】ボカロP別人気曲メドレー", "v": 124305, "d": 802.09, "len": 60, "voca": true, "cov": false}, {"id": "kUgOaqIyILA", "t": "【2008年】年代別ボカロ人気曲メドレー", "v": 121864, "d": 957.71, "len": 60, "voca": true, "cov": false}, {"id": "PiAq240gGKM", "t": "【R Sound Design】ボカロP別人気曲メドレー", "v": 120462, "d": 861.84, "len": 58, "voca": true, "cov": false}, {"id": "BvvJQa5cx5I", "t": "【ジャンル別】カッコいい和風ロックなボカロ曲メドレー③", "v": 118344, "d": 523.71, "len": 60, "voca": true, "cov": false}, {"id": "HB8erPuZiIM", "t": "【大漠波新】ボカロP別人気曲メドレー", "v": 117605, "d": 746.09, "len": 60, "voca": true, "cov": false}, {"id": "P3IYbqFxhaI", "t": "【2014年】年代別ボカロ人気曲メドレー", "v": 116410, "d": 939.71, "len": 59, "voca": true, "cov": false}, {"id": "2xy2HilKEXI", "t": "【ぬゆり】ボカロP別人気曲メドレー", "v": 115557, "d": 858.09, "len": 60, "voca": true, "cov": false}, {"id": "t3HlmzA6FJo", "t": "【mothy_悪ノP】ボカロP別人気曲メドレー", "v": 115294, "d": 856.84, "len": 60, "voca": true, "cov": false}, {"id": "ztblap3SK7I", "t": "【テーマ別】少し切ない夏の終わりに聞きたいボカロ曲メドレー③", "v": 114788, "d": 534.71, "len": 60, "voca": true, "cov": false}, {"id": "_wQczDYtMhI", "t": "【バルーン】ボカロP別人気曲メドレー", "v": 113627, "d": 886.09, "len": 60, "voca": true, "cov": false}, {"id": "Lg3DPTPWI9Y", "t": "【Orangestar】ボカロP別人気曲メドレー Part.1", "v": 110369, "d": 831.84, "len": 60, "voca": true, "cov": false}, {"id": "w_A45MiED3o", "t": "【ピノキオピー】ボカロP別人気曲メドレー Part.2", "v": 108716, "d": 849.84, "len": 60, "voca": true, "cov": false}, {"id": "f154SXt1dgw", "t": "【2009年】年代別ボカロ人気曲メドレー", "v": 107994, "d": 953.71, "len": 57, "voca": true, "cov": false}, {"id": "Q20Q5Hd9pIA", "t": "【カルロス袴田(サイゼP) 】ボカロP別人気曲メドレー", "v": 106452, "d": 835.58, "len": 60, "voca": true, "cov": false}, {"id": "C-StPE1IXiQ", "t": "【2007年】ボカロ人気曲メドレー【作業用BGM】", "v": 105947, "d": 1056.59, "len": 3873, "voca": true, "cov": false}, {"id": "z7u6hzKayfU", "t": "【ユリイ・カノン】ボカロP別人気曲メドレー", "v": 105348, "d": 817.8, "len": 60, "voca": true, "cov": false}, {"id": "Yim15m9Rj1c", "t": "【2024年】年代別ボカロ人気曲メドレー Part.4", "v": 104648, "d": 557.09, "len": 60, "voca": true, "cov": false}, {"id": "bA9HAW2hgvw", "t": "【halyosy】ボカロP別人気曲メドレー", "v": 103638, "d": 863.84, "len": 60, "voca": true, "cov": false}, {"id": "fEmzbztziMc", "t": "【DECO*27】ボカロP別人気曲メドレー Part.2", "v": 103295, "d": 840.84, "len": 60, "voca": true, "cov": false}, {"id": "izfckgVQptM", "t": "【れるりり】ボカロP別人気曲メドレー Part.1", "v": 101647, "d": 816.09, "len": 60, "voca": true, "cov": false}, {"id": "_gQSyDb_pCw", "t": "【テーマ別】雨の日に聞きたいボカロ曲メドレー①", "v": 97142, "d": 543.71, "len": 60, "voca": true, "cov": false}, {"id": "nQOssQJSM0A", "t": "【chinozo】ボカロP別人気曲メドレー", "v": 95862, "d": 865.09, "len": 60, "voca": true, "cov": false}, {"id": "YvkkAokJAZY", "t": "【40mP】ボカロP別人気曲メドレー", "v": 92591, "d": 905.84, "len": 60, "voca": true, "cov": false}, {"id": "zO9cUQBLu6M", "t": "【じん(自然の敵P)】ボカロP別人気曲メドレー Part.2", "v": 91464, "d": 726.84, "len": 60, "voca": true, "cov": false}, {"id": "v84vLiLpGaU", "t": "【キノシタ】ボカロP別人気曲メドレー", "v": 91293, "d": 828.84, "len": 60, "voca": true, "cov": false}, {"id": "9OAN8lc_yjA", "t": "【2017年】ボカロ人気曲メドレー【作業用BGM】", "v": 91124, "d": 902.09, "len": 10118, "voca": true, "cov": false}, {"id": "xgltecopY30", "t": "【MARETU】ボカロP別人気曲メドレー Part.2", "v": 91107, "d": 810.09, "len": 60, "voca": true, "cov": false}, {"id": "taE64mim5Kg", "t": "【2007年】年代別ボカロ人気曲メドレー", "v": 90222, "d": 960.71, "len": 59, "voca": true, "cov": false}, {"id": "4yMxju_RjVo", "t": "【kemu】ボカロP別人気曲メドレー", "v": 89294, "d": 889.84, "len": 60, "voca": true, "cov": false}, {"id": "SJiSrJT-cvc", "t": "【Mitchie M】ボカロP別人気曲メドレー", "v": 86901, "d": 854.84, "len": 60, "voca": true, "cov": false}, {"id": "04P6UZoM-KY", "t": "【2019年】ボカロ人気曲メドレー【作業用BGM】", "v": 86356, "d": 900.09, "len": 8702, "voca": true, "cov": false}, {"id": "OgiPxOKb17A", "t": "【2024年】年代別ボカロ人気曲メドレー Part.1", "v": 86351, "d": 562.71, "len": 60, "voca": true, "cov": false}, {"id": "JXw-rzlU5nk", "t": "【ラマーズP】ボカロP別人気曲メドレー", "v": 85777, "d": 772.84, "len": 60, "voca": true, "cov": false}, {"id": "4YDCY13f0fA", "t": "【テーマ別】都会系!?夜に聞きたいエモいボカロ曲メドレー③", "v": 84054, "d": 593.71, "len": 60, "voca": true, "cov": false}, {"id": "Pywy9xTj8jA", "t": "【Kanaria】ボカロP別人気曲メドレー", "v": 83603, "d": 859.84, "len": 60, "voca": true, "cov": false}, {"id": "dVGNdbXfJ_4", "t": "【歌ってみた】ボカロ人気曲メドレー【セルフカバー】Part.21", "v": 82186, "d": 681.71, "len": 60, "voca": true, "cov": true}, {"id": "ICWaTdWaSPc", "t": "【歌ってみた】ボカロ人気曲メドレー【セルフカバー】Part.3", "v": 80612, "d": 714.71, "len": 60, "voca": true, "cov": true}, {"id": "EeibBE_rAqo", "t": "【2008年】ボカロ人気曲メドレー【作業用BGM】", "v": 78846, "d": 1055.59, "len": 4031, "voca": true, "cov": false}, {"id": "zsSbQoFi5cc", "t": "【GYARI(ココアシガレットP)】ボカロP別人気曲メドレー", "v": 78261, "d": 789.84, "len": 60, "voca": true, "cov": false}, {"id": "u6SqsQaUKVA", "t": "【メドミア】ボカロP別人気曲メドレー", "v": 77611, "d": 798.92, "len": 60, "voca": true, "cov": false}, {"id": "o3SaMZRTMIs", "t": "【椎名もた(ぽわぽわP)】ボカロP別人気曲メドレー", "v": 77287, "d": 823.09, "len": 60, "voca": true, "cov": false}, {"id": "HrQTly12Y88", "t": "【柊キライ】ボカロP別人気曲メドレー", "v": 76853, "d": 838.84, "len": 60, "voca": true, "cov": false}, {"id": "ZkVn4efJhIs", "t": "【テーマ別】地雷系!?明るくて病み可愛いボカロ曲メドレー①", "v": 76505, "d": 628.71, "len": 60, "voca": true, "cov": false}, {"id": "ZJ2w4LwWxiQ", "t": "【2020年】ボカロ人気曲メドレー【作業用BGM】", "v": 75449, "d": 899.09, "len": 8347, "voca": true, "cov": false}, {"id": "Sqtph-ncOVE", "t": "【テーマ別】地雷系!?明るくて病み可愛いボカロ曲メドレー③", "v": 73741, "d": 597.67, "len": 60, "voca": true, "cov": false}, {"id": "9eLEEK9lE5Q", "t": "【はるまきごはん 】ボカロP別人気曲メドレー", "v": 73622, "d": 833.84, "len": 60, "voca": true, "cov": false}, {"id": "pO5TVFBG-LE", "t": "【ジャンル別】エレクトロスウィングなボカロ曲メドレー②", "v": 73593, "d": 583.71, "len": 60, "voca": true, "cov": false}, {"id": "YeCNOLpyZmE", "t": "【歌ってみた】ボカロ人気曲メドレー【セルフカバー】Part.1", "v": 72924, "d": 719.71, "len": 60, "voca": true, "cov": true}, {"id": "FsTN8ahbAw8", "t": "【テーマ別】切ない恋愛ソングボカロメドレー③", "v": 72730, "d": 537.71, "len": 60, "voca": true, "cov": false}, {"id": "X8bctAsQYsw", "t": "【kz】ボカロP別人気曲メドレー", "v": 71314, "d": 842.84, "len": 60, "voca": true, "cov": false}, {"id": "GMStHRtoVjI", "t": "【歌ってみた】ボカロ人気曲メドレー【セルフカバー】Part.29", "v": 70970, "d": 667.71, "len": 60, "voca": true, "cov": true}, {"id": "xDxZftmEChY", "t": "【2018年】ボカロ人気曲メドレー【作業用BGM】", "v": 69718, "d": 901.09, "len": 9363, "voca": true, "cov": false}, {"id": "cc73yQKKGa8", "t": "【OSTER project】ボカロP別人気曲メドレー", "v": 69568, "d": 870.84, "len": 58, "voca": true, "cov": false}, {"id": "2x3ejqs5f9I", "t": "【歌ってみた】ボカロ人気曲メドレー【セルフカバー】Part.25", "v": 68915, "d": 674.71, "len": 60, "voca": true, "cov": true}, {"id": "N0EuQcK4u7E", "t": "【ガルナ(オワタP)】ボカロP別人気曲メドレー", "v": 67166, "d": 793.84, "len": 60, "voca": true, "cov": false}, {"id": "jw5ejnOmKvE", "t": "【2024年】年代別ボカロ人気曲メドレー Part.2", "v": 66495, "d": 560.71, "len": 60, "voca": true, "cov": false}, {"id": "KNOKS6KdmCY", "t": "【Aqu3ra】ボカロP別人気曲メドレー", "v": 66388, "d": 847.84, "len": 60, "voca": true, "cov": false}, {"id": "CLlBST8JYCQ", "t": "【歌ってみた】ボカロ人気曲メドレー【セルフカバー】Part.15", "v": 66206, "d": 691.71, "len": 60, "voca": true, "cov": true}, {"id": "aBdMi1kRwU8", "t": "【全てあなたの所為です。】ボカロP別人気曲メドレー", "v": 65728, "d": 796.09, "len": 55, "voca": true, "cov": false}, {"id": "Ntc9Cgghiag", "t": "【れるりり】ボカロP別人気曲メドレー Part.2", "v": 65674, "d": 782.84, "len": 60, "voca": true, "cov": false}, {"id": "VfgFq-uKgwQ", "t": "【テーマ別】透明感のある優しいボカロ曲メドレー①", "v": 63950, "d": 617.71, "len": 59, "voca": true, "cov": false}, {"id": "xiUrX5Sy91s", "t": "【Orangestar】ボカロP別人気曲メドレー Part.2", "v": 63807, "d": 814.84, "len": 60, "voca": true, "cov": false}, {"id": "MhAHYmRQZhA", "t": "【歌ってみた】ボカロ人気曲メドレー【セルフカバー】Part.9", "v": 63601, "d": 702.71, "len": 60, "voca": true, "cov": true}, {"id": "szzH9_79xoI", "t": "【なきそ】ボカロP別人気曲メドレー", "v": 63128, "d": 763.84, "len": 60, "voca": true, "cov": false}, {"id": "axTsfNQEG5M", "t": "【ジャンル別】軽快なテクノポップのボカロ曲メドレー③", "v": 63093, "d": 540.71, "len": 60, "voca": true, "cov": false}, {"id": "pLxBpc9jlIE", "t": "【テーマ別】透明感のある優しいボカロ曲メドレー②", "v": 62801, "d": 604.57, "len": 60, "voca": true, "cov": false}, {"id": "d3CuKV6cPzM", "t": "【ジャンル別】お洒落なリズムのエレクトロスウィングなボカロ曲メドレー①", "v": 62563, "d": 599.09, "len": 60, "voca": true, "cov": false}, {"id": "lNWqqB_KWjk", "t": "【テーマ別】夕暮れ時に聞きたいボカロ曲メドレー③", "v": 62559, "d": 548.71, "len": 60, "voca": true, "cov": false}, {"id": "3Xa5oSy5jKA", "t": "【南ノ南】ボカロP別人気曲メドレー", "v": 60893, "d": 756.84, "len": 60, "voca": true, "cov": false}, {"id": "Or41U1ZSZsg", "t": "【HoneyWorks】ボカロP別人気曲メドレー Part.1", "v": 60456, "d": 810.84, "len": 60, "voca": true, "cov": false}, {"id": "KHKgXs1RSco", "t": "【カラスヤサボウ】ボカロP別人気曲メドレー", "v": 60373, "d": 774.09, "len": 60, "voca": true, "cov": false}, {"id": "_U7cigWW7jo", "t": "【TOKOTOKO(西沢さんP)】ボカロP別人気曲メドレー", "v": 60143, "d": 812.84, "len": 60, "voca": true, "cov": false}, {"id": "4y6bBfq7KbI", "t": "【和田たけあき(くらげP)】ボカロP別人気曲メドレー", "v": 59865, "d": 803.84, "len": 60, "voca": true, "cov": false}, {"id": "po1-coJykjY", "t": "【CRUSHER-P,Circus-P,KIRA】ボカロP別人気曲メドレー", "v": 59634, "d": 824.84, "len": 60, "voca": true, "cov": false}, {"id": "gOYxbQLNvEA", "t": "【カンザキイオリ】ボカロP別人気曲メドレー", "v": 59342, "d": 844.09, "len": 60, "voca": true, "cov": false}, {"id": "eZW7gZIeyMI", "t": "【ピノキオピー】ボカロP別人気曲メドレー Part.3", "v": 59096, "d": 723.84, "len": 60, "voca": true, "cov": false}, {"id": "g7bp5nijN_0", "t": "【john】ボカロP別人気曲メドレー", "v": 58870, "d": 796.84, "len": 60, "voca": true, "cov": false}, {"id": "aDSS67Lo-5c", "t": "【23.exe】ボカロP別人気曲メドレー", "v": 57426, "d": 813.84, "len": 60, "voca": true, "cov": false}, {"id": "ITx6NpfFXGw", "t": "【ぐちり】ボカロP別人気曲メドレー", "v": 57404, "d": 742.84, "len": 60, "voca": true, "cov": false}, {"id": "RikrWrrHLmg", "t": "【Last Note.】ボカロP別人気曲メドレー", "v": 56163, "d": 777.8, "len": 60, "voca": true, "cov": false}, {"id": "l6EqVlNL0v4", "t": "【LonePi】ボカロP別人気曲メドレー", "v": 54443, "d": 791.84, "len": 60, "voca": true, "cov": false}, {"id": "nhzjeASwrE8", "t": "【Omoi】ボカロP別人気曲メドレー", "v": 53986, "d": 807.84, "len": 60, "voca": true, "cov": false}, {"id": "tvZSFKEXXcA", "t": "【テーマ別】切ない恋愛ソングのボカロ曲メドレー①", "v": 53687, "d": 595.71, "len": 60, "voca": true, "cov": false}, {"id": "IoB9r8kWLY0", "t": "【DIVELA】ボカロP別人気曲メドレー", "v": 53486, "d": 767.09, "len": 60, "voca": true, "cov": false}, {"id": "FeKYb7datEs", "t": "【歌ってみた】ボカロ人気曲メドレー【セルフカバー】Part.20", "v": 52825, "d": 683.09, "len": 60, "voca": true, "cov": true}, {"id": "bjQeBa6Hy_Q", "t": "【歌ってみた】ボカロ人気曲メドレー【セルフカバー】Part.32", "v": 52772, "d": 662.09, "len": 60, "voca": true, "cov": true}, {"id": "ZtefTVULatQ", "t": "【2015年】ボカロ人気曲メドレー【作業用BGM】", "v": 52604, "d": 904.09, "len": 7529, "voca": true, "cov": false}, {"id": "LVFoIpiTQ60", "t": "【てにをは】ボカロP別人気曲メドレー", "v": 52051, "d": 775.84, "len": 54, "voca": true, "cov": false}, {"id": "n1o-KvpfsEc", "t": "【Guiano】ボカロP別人気曲メドレー", "v": 51771, "d": 788.09, "len": 60, "voca": true, "cov": false}, {"id": "UtI22oLzpOQ", "t": "【テーマ別】少し切ない夏の終わりに聞きたいボカロ曲メドレー①", "v": 51669, "d": 609.71, "len": 55, "voca": true, "cov": false}, {"id": "IsrHWzOg2Ls", "t": "【柊マグネタイト】ボカロP別人気曲メドレー", "v": 50548, "d": 781.09, "len": 60, "voca": true, "cov": false}, {"id": "n4LJu9_22sM", "t": "【DECO*27】ボカロP別人気曲メドレー Part.3", "v": 50412, "d": 721.84, "len": 60, "voca": true, "cov": false}, {"id": "MOLZUoaUfpE", "t": "【歌ってみた】ボカロ人気曲メドレー【セルフカバー】Part.6", "v": 50325, "d": 707.71, "len": 60, "voca": true, "cov": true}, {"id": "UAsXQDrI5a0", "t": "【ジャンル別】カッコいい和風ロックなボカロ曲メドレー①", "v": 50142, "d": 606.09, "len": 60, "voca": true, "cov": false}, {"id": "C6HAVA0m2u0", "t": "【テーマ別】都会系!?夜に聞きたいエモいボカロ曲メドレー①", "v": 48808, "d": 625.71, "len": 60, "voca": true, "cov": false}, {"id": "vlO12IQPark", "t": "【wowaka】ボカロP別人気曲メドレー", "v": 48783, "d": 725.09, "len": 58, "voca": true, "cov": false}, {"id": "Mb3r-2-XUxk", "t": "【マイキP】ボカロP別人気曲メドレー", "v": 48378, "d": 749.84, "len": 60, "voca": true, "cov": false}, {"id": "roPUTHMhcvQ", "t": "【ジャンル別】カッコいい和風ロックなボカロ曲メドレー②", "v": 48245, "d": 586.71, "len": 60, "voca": true, "cov": false}, {"id": "agTAvS_fa_4", "t": "【テーマ別】優しい透明感のあるボカロ曲メドレー③", "v": 48091, "d": 576.71, "len": 60, "voca": true, "cov": false}, {"id": "xjRMMrUcV8w", "t": "【ジャンル別】軽快なテクノポップのボカロ曲メドレー②", "v": 47125, "d": 600.71, "len": 60, "voca": true, "cov": false}, {"id": "3iUXKgB0hBw", "t": "【歌ってみた】ボカロ人気曲メドレー【セルフカバー】Part.13", "v": 46319, "d": 695.71, "len": 60, "voca": true, "cov": true}, {"id": "wuUMIN7Dk54", "t": "【青谷】ボカロP別人気曲メドレー", "v": 45832, "d": 729.84, "len": 60, "voca": true, "cov": false}, {"id": "wEkapWD60nM", "t": "【歌ってみた】ボカロ人気曲メドレー【セルフカバー】Part.2", "v": 45381, "d": 716.71, "len": 60, "voca": true, "cov": true}, {"id": "ZGbtdOmhjFw", "t": "【歌ってみた】ボカロ人気曲メドレー【セルフカバー】Part.4", "v": 44904, "d": 712.71, "len": 60, "voca": true, "cov": true}, {"id": "0cy8X_Yiq8w", "t": "【keeno】ボカロP別人気曲メドレー", "v": 44508, "d": 800.84, "len": 60, "voca": true, "cov": false}, {"id": "AucsVCRVwSA", "t": "【歌ってみた】ボカロ人気曲メドレー【セルフカバー】Part.12", "v": 44370, "d": 697.09, "len": 60, "voca": true, "cov": true}, {"id": "JtZjCI4hGPs", "t": "【ワンダフル☆オポチュニティ！】ボカロP別人気曲メドレー", "v": 42859, "d": 784.84, "len": 60, "voca": true, "cov": false}, {"id": "6mqbxg1jzSc", "t": "【原口沙輔】ボカロP別人気曲メドレー", "v": 42745, "d": 754.84, "len": 60, "voca": true, "cov": false}, {"id": "SsAIXInyy_4", "t": "【とあ】ボカロP別人気曲メドレー", "v": 42394, "d": 753.09, "len": 60, "voca": true, "cov": false}, {"id": "6fqR0Dxkt8c", "t": "【歌ってみた】ボカロ人気曲メドレー【セルフカバー】Part.17", "v": 41885, "d": 688.71, "len": 60, "voca": true, "cov": true}, {"id": "dX9cbes8EC8", "t": "【テーマ別】切ない恋愛ソングボカロメドレー②", "v": 41302, "d": 579.0, "len": 60, "voca": true, "cov": false}, {"id": "sPY5gWqmVCk", "t": "【テーマ別】少し切ない夏の終わりに聞きたいボカロ曲メドレー②", "v": 41233, "d": 590.71, "len": 60, "voca": true, "cov": false}, {"id": "Fb_LwD7Ny00", "t": "【歌ってみた】ボカロ人気曲メドレー【セルフカバー】Part.23", "v": 40964, "d": 677.71, "len": 60, "voca": true, "cov": true}, {"id": "jD-CzoxFU6M", "t": "【水野あつ】ボカロP別人気曲メドレー", "v": 40359, "d": 733.84, "len": 59, "voca": true, "cov": false}, {"id": "qcJmT8zV31w", "t": "【真島ゆろ】ボカロP別人気曲メドレー", "v": 40175, "d": 760.09, "len": 60, "voca": true, "cov": false}, {"id": "VsdGF0K1298", "t": "【ゆこぴ】ボカロP別人気曲メドレー", "v": 39779, "d": 768.84, "len": 60, "voca": true, "cov": false}, {"id": "IGmM2_bZsHQ", "t": "【ポリスピカデリー】ボカロP別人気曲メドレー", "v": 39657, "d": 765.84, "len": 60, "voca": true, "cov": false}, {"id": "BOucd_c4Hr4", "t": "【歌ってみた】ボカロ人気曲メドレー【セルフカバー】Part.8", "v": 38582, "d": 704.09, "len": 60, "voca": true, "cov": true}, {"id": "RAjk27yGpPI", "t": "【羽生まゐご】ボカロP別人気曲メドレー", "v": 38320, "d": 761.84, "len": 60, "voca": true, "cov": false}, {"id": "a3JOUMLMta8", "t": "【歌ってみた】ボカロ人気曲メドレー【セルフカバー】Part.45", "v": 38200, "d": 637.71, "len": 60, "voca": true, "cov": true}, {"id": "hW0Rrr5wGFI", "t": "【香椎モイミ】ボカロP別人気曲メドレー", "v": 37712, "d": 739.09, "len": 60, "voca": true, "cov": false}, {"id": "telUerHQg7o", "t": "【歌ってみた】ボカロ人気曲メドレー【セルフカバー】Part.47", "v": 36012, "d": 634.09, "len": 60, "voca": true, "cov": true}, {"id": "yI2cd7Al0Z0", "t": "【ツミキ】ボカロP別人気曲メドレー", "v": 35992, "d": 732.09, "len": 60, "voca": true, "cov": false}, {"id": "0yNeP0r6K6g", "t": "【歌ってみた】ボカロ人気曲メドレー【セルフカバー】Part.30", "v": 35826, "d": 665.71, "len": 60, "voca": true, "cov": true}, {"id": "HhafmMOtSDQ", "t": "【Kai】ボカロP別人気曲メドレー", "v": 34791, "d": 747.84, "len": 60, "voca": true, "cov": false}, {"id": "lWed481XQNU", "t": "【テーマ別】夕方に聞きたいボカロ曲メドレー②", "v": 34763, "d": 572.71, "len": 60, "voca": true, "cov": false}, {"id": "dPA7Rm1xvvw", "t": "【歌ってみた】ボカロ人気曲メドレー【セルフカバー】Part.26", "v": 34745, "d": 672.71, "len": 60, "voca": true, "cov": true}, {"id": "Ym0aGrx10Uc", "t": "【有機酸】ボカロP別人気曲メドレー", "v": 34711, "d": 786.84, "len": 60, "voca": true, "cov": false}, {"id": "x46l1sdJDoY", "t": "【梅とら】ボカロP別人気曲メドレー", "v": 34515, "d": 805.84, "len": 60, "voca": true, "cov": false}, {"id": "u8UxRdRS4L0", "t": "【歌ってみた】ボカロ人気曲メドレー【セルフカバー】Part.31", "v": 34158, "d": 663.71, "len": 60, "voca": true, "cov": true}, {"id": "FdhyUqg4UgY", "t": "【歌ってみた】ボカロ人気曲メドレー【セルフカバー】Part.19", "v": 33249, "d": 684.71, "len": 60, "voca": true, "cov": true}, {"id": "U3yvlguD6Dw", "t": "【歌ってみた】ボカロ人気曲メドレー【セルフカバー】Part.46", "v": 32715, "d": 635.71, "len": 60, "voca": true, "cov": true}, {"id": "_yLKqEvc8PM", "t": "【大沼パセリ】ボカロP別人気曲メドレー", "v": 32540, "d": 751.84, "len": 60, "voca": true, "cov": false}, {"id": "U4nXIZMp8-Y", "t": "【歌ってみた】ボカロ人気曲メドレー【セルフカバー】Part.11", "v": 32348, "d": 698.71, "len": 60, "voca": true, "cov": true}, {"id": "Ryw95M2pPA0", "t": "【HoneyWorks】ボカロP別人気曲メドレー Part.3", "v": 32232, "d": 728.84, "len": 59, "voca": true, "cov": false}, {"id": "IDtz2lfy2p4", "t": "【歌ってみた】ボカロ人気曲メドレー【セルフカバー】Part.40", "v": 32192, "d": 646.71, "len": 60, "voca": true, "cov": true}, {"id": "PBoeBqkeiI4", "t": "【うたたP】ボカロP別人気曲メドレー", "v": 31817, "d": 744.84, "len": 60, "voca": true, "cov": false}, {"id": "Ly9ozgsy8YI", "t": "【一二三】ボカロP別人気曲メドレー", "v": 31745, "d": 758.84, "len": 60, "voca": true, "cov": false}, {"id": "73GuYnGhd9Y", "t": "【テーマ別】夕暮れ時に聞きたいボカロ曲メドレー①", "v": 31705, "d": 602.71, "len": 60, "voca": true, "cov": false}, {"id": "bp9p0cAqZuI", "t": "【HoneyWorks】ボカロP別人気曲メドレー Part.2", "v": 31389, "d": 779.84, "len": 60, "voca": true, "cov": false}, {"id": "vk3U1NSQbQY", "t": "【まさ】ボカロP別人気曲メドレー", "v": 31338, "d": 737.84, "len": 60, "voca": true, "cov": false}, {"id": "vH2BZ9fUx3w", "t": "【164】ボカロP別人気曲メドレー", "v": 31189, "d": 735.84, "len": 60, "voca": true, "cov": false}, {"id": "4IQQTUkr3mU", "t": "【ジャンル別】軽快なテクノポップのボカロ曲メドレー①", "v": 31053, "d": 614.71, "len": 60, "voca": true, "cov": false}, {"id": "TLRpQ-ujzyI", "t": "【歌ってみた】ボカロ人気曲メドレー【セルフカバー】Part.34", "v": 31025, "d": 658.71, "len": 60, "voca": true, "cov": true}, {"id": "UTwsVDVKMCk", "t": "【歌ってみた】ボカロ人気曲メドレー【セルフカバー】Part.14", "v": 29438, "d": 693.71, "len": 60, "voca": true, "cov": true}, {"id": "7G2qwalklss", "t": "【歌ってみた】ボカロ人気曲メドレー【セルフカバー】Part.44", "v": 29333, "d": 639.71, "len": 60, "voca": true, "cov": true}, {"id": "9YGljIIVzFE", "t": "【歌ってみた】ボカロ人気曲メドレー【セルフカバー】Part.39", "v": 28485, "d": 649.71, "len": 60, "voca": true, "cov": true}, {"id": "puz8XpTzqew", "t": "【歌ってみた】ボカロ人気曲メドレー【セルフカバー】Part.24", "v": 28310, "d": 676.09, "len": 60, "voca": true, "cov": true}, {"id": "d45nt20W9RE", "t": "【歌ってみた】ボカロ人気曲メドレー【セルフカバー】Part.43", "v": 27758, "d": 641.09, "len": 60, "voca": true, "cov": true}, {"id": "Z5jwpoZfuNE", "t": "【歌ってみた】ボカロ人気曲メドレー【セルフカバー】Part.22", "v": 27490, "d": 679.71, "len": 60, "voca": true, "cov": true}, {"id": "8cdZvTl0zsQ", "t": "【歌ってみた】ボカロ人気曲メドレー【セルフカバー】Part.18", "v": 27175, "d": 686.71, "len": 60, "voca": true, "cov": true}, {"id": "9JictBZkEOY", "t": "【歌ってみた】ボカロ人気曲メドレー【セルフカバー】Part.28", "v": 26623, "d": 669.09, "len": 56, "voca": true, "cov": true}, {"id": "nqH1d8yT_6U", "t": "【歌ってみた】ボカロ人気曲メドレー【セルフカバー】Part.7", "v": 26181, "d": 705.71, "len": 60, "voca": true, "cov": true}, {"id": "BxL8_RNKnWE", "t": "【歌ってみた】ボカロ人気曲メドレー【セルフカバー】Part.10", "v": 25709, "d": 700.71, "len": 60, "voca": true, "cov": true}, {"id": "K1NjkwgySDE", "t": "【歌ってみた】ボカロ人気曲メドレー【セルフカバー】Part.37", "v": 25511, "d": 653.71, "len": 60, "voca": true, "cov": true}, {"id": "zzj1ZPSY1Tk", "t": "【歌ってみた】ボカロ人気曲メドレー【セルフカバー】Part.33", "v": 24968, "d": 660.71, "len": 59, "voca": true, "cov": true}, {"id": "i33Cof5dt18", "t": "【歌ってみた】ボカロ人気曲メドレー【セルフカバー】Part.16", "v": 24410, "d": 690.09, "len": 60, "voca": true, "cov": true}, {"id": "xBf7xQB8jXc", "t": "【歌ってみた】ボカロ人気曲メドレー【セルフカバー】Part.37", "v": 24033, "d": 651.71, "len": 60, "voca": true, "cov": true}, {"id": "SQiCfwjcCwk", "t": "【歌ってみた】ボカロ人気曲メドレー【セルフカバー】Part.42", "v": 23824, "d": 642.71, "len": 60, "voca": true, "cov": true}, {"id": "Y2cWBimRzHo", "t": "【歌ってみた】ボカロ人気曲メドレー【セルフカバー】Part.35", "v": 23070, "d": 656.71, "len": 60, "voca": true, "cov": true}, {"id": "z4XHg3sC9fc", "t": "【歌ってみた】ボカロ人気曲メドレー【セルフカバー】Part.36", "v": 21786, "d": 655.09, "len": 60, "voca": true, "cov": true}, {"id": "vsF5fAmDa40", "t": "【歌ってみた】ボカロ人気曲メドレー【セルフカバー】Part.27", "v": 21569, "d": 670.71, "len": 60, "voca": true, "cov": true}, {"id": "Gtwfu8d3X5k", "t": "【歌ってみた】ボカロ人気曲メドレー【セルフカバー】Part.41", "v": 20915, "d": 644.71, "len": 60, "voca": true, "cov": true}]}