{"name": "GYARI", "updated": "2026-07-07", "fullFetched": "2026-07-07", "totalFetched": 42, "videos": [{"id": "tyneiz9FRMw", "t": "アカリがやってきたぞっ", "v": 26555172, "d": 2844.51, "len": 302, "voca": true, "cov": false}, {"id": "OVuYIMa5XBw", "t": "何でも言うことを聞いてくれるアカネチャン", "v": 25772739, "d": 3112.44, "len": 285, "voca": true, "cov": false}, {"id": "pfkBYHFZAt8", "t": "絶対にチョコミントを食べるアオイチャン", "v": 15145736, "d": 2523.3, "len": 357, "voca": true, "cov": false}, {"id": "5uFrdGMo684", "t": "永遠にゲームで対戦したいキリタン", "v": 14596525, "d": 2381.22, "len": 330, "voca": true, "cov": false}, {"id": "M20SfPdzlQ0", "t": "無限にホメてくれる桜乃そら先生", "v": 8007602, "d": 2747.3, "len": 301, "voca": true, "cov": false}, {"id": "czizBiAhHiI", "t": "ボーカロイドたちがただ叫ぶだけ", "v": 7416760, "d": 3560.31, "len": 1402, "voca": true, "cov": false}, {"id": "-iFEKeULaIo", "t": "ボーカロイドたちがただﾃｯﾃｰﾃﾚｯﾃｰするだけ", "v": 6380701, "d": 3788.08, "len": 1220, "voca": true, "cov": false}, {"id": "u8Vs_tfm8Jc", "t": "楽曲バトル！紲星イキリと化した後輩", "v": 4709027, "d": 2888.13, "len": 316, "voca": true, "cov": false}, {"id": "siIE8i48hlg", "t": "ボーカロイドたちが2コードくり返してﾃｯﾃｰﾃﾚｯﾃｰとか叫ぶだけ", "v": 3714261, "d": 3356.17, "len": 1819, "voca": true, "cov": false}, {"id": "KYQ2fu8eixM", "t": "ボーカロイドたちがただ2コードくりかえすだけ", "v": 3472316, "d": 3978.31, "len": 1417, "voca": true, "cov": false}, {"id": "BbyqEMSDuww", "t": "ずんだもん「チャンネル登録よろしくお願いします」 #チャンネル登録なのだ", "v": 2590855, "d": 1060.17, "len": 334, "voca": true, "cov": false}, {"id": "YzuWMyd7Pjk", "t": "【宮舞モカ】進捗ダメダメです【ＭＶ】", "v": 1726905, "d": 556.17, "len": 261, "voca": true, "cov": false}, {"id": "Zj8lmg6NpOg", "t": "花隈の歌は可愛いし小春六花はマジでうるさい", "v": 1497324, "d": 920.47, "len": 275, "voca": true, "cov": false}, {"id": "xT5s6PYroFI", "t": "うちのリンさんがYellow(livetune)をアレンジしたようです", "v": 1434827, "d": 3009.09, "len": 230, "voca": true, "cov": true}, {"id": "paRwZI6ZYF4", "t": "【結月ゆかり】月旅【オリジナル曲】", "v": 1277299, "d": 4208.13, "len": 320, "voca": true, "cov": false}, {"id": "satZx43Sv_0", "t": "【重音テトSV】ドリル無双。～異世界転生して神からドリルを授かった私は、王女を助けたりニセ勇者を追放したり魔王を討伐して", "v": 1096217, "d": 695.24, "len": 280, "voca": true, "cov": false}, {"id": "6gIXh0-e2R0", "t": "【鏡音リン】10年後の月光ステージ【セルフカバー】", "v": 957020, "d": 2404.69, "len": 616, "voca": true, "cov": true}, {"id": "vme3SGv7jQU", "t": "Scramble Full Panic Sessions", "v": 903200, "d": 4347.18, "len": 587, "voca": false, "cov": false}, {"id": "P_sBALzyd9k", "t": "ネタが無いよ～ / 重音テト", "v": 600043, "d": 313.26, "len": 172, "voca": true, "cov": false}, {"id": "PFjnhRsJgHU", "t": "私の酸素を吸わないでほしい ／ Vo.羽渦ミウネル", "v": 547466, "d": 1170.13, "len": 269, "voca": false, "cov": false}, {"id": "AOuA6_hKWIs", "t": "Splatoon1周年ナワバリバトル中にかっこいいシオカラ節が流れた件", "v": 438947, "d": 3690.63, "len": 221, "voca": false, "cov": false}, {"id": "hpKAg4X30KM", "t": "ありきたりな恋の歌【六花OFF版】 ／ Vo.花隈千冬", "v": 288684, "d": 909.24, "len": 275, "voca": false, "cov": false}, {"id": "Hm3Alq0MDT0", "t": "2017.9.10 GYARI BAND LIVE! - GYABAN", "v": 280954, "d": 3218.13, "len": 141, "voca": false, "cov": false}, {"id": "-TPQoj29ttM", "t": "Scramble Full Panic", "v": 278315, "d": 4347.18, "len": 241, "voca": false, "cov": false}, {"id": "jCLv97IrVWs", "t": "【MV】クソデッカ★オーディエンサー / 夏色花梨＆小春六花", "v": 276000, "d": 325.26, "len": 257, "voca": true, "cov": false}, {"id": "ziw6lJrViVs", "t": "花隈のワニを磨く小春六花 #shorts", "v": 255668, "d": 909.16, "len": 10, "voca": false, "cov": false}, {"id": "2Pd-SDGT-Bg", "t": "VOMS Opening Movie｜ #voms_project", "v": 226570, "d": 2279.3, "len": 223, "voca": false, "cov": false}, {"id": "rU-ZvdijZ2Q", "t": "進捗カスDISCO #shorts", "v": 224944, "d": 521.1, "len": 25, "voca": true, "cov": false}, {"id": "cWBPbwyd4Cg", "t": "GYARIバンド「GYABAN」再始動に関する告知配信", "v": 77255, "d": 2332.5, "len": 3629, "voca": false, "cov": false}, {"id": "VXCaDJUrrmg", "t": "【打ち上げ】2020.9.19 GYARI BAND NET LIVE!!!【オーディオコメンタリー】 #GYABAN", "v": 64030, "d": 2114.07, "len": 10794, "voca": false, "cov": false}, {"id": "tQViR6i0aD0", "t": "テスト配信と告知と飲み会と鳳凰美田(ゆず) #GYABAN", "v": 55337, "d": 2122.21, "len": 4039, "voca": false, "cov": false}, {"id": "fKbGyhepJgk", "t": "色彩の共鳴 ／ Vo. AHS Family", "v": 41573, "d": 97.26, "len": 261, "voca": false, "cov": false}, {"id": "OMykcwcMl68", "t": "🔴ネタが無いクソデッカ3Dライブ配信", "v": 17699, "d": 279.12, "len": 3870, "voca": false, "cov": false}, {"id": "B90lJUSi0y0", "t": "🔴丸の内みたいな進行で適当に遊ぶ配信", "v": 15136, "d": 426.04, "len": 5114, "voca": false, "cov": false}, {"id": "hiqJ6lI6VdA", "t": "🔴新しい音源とキーボード買っﾎﾎﾎｗ", "v": 13325, "d": 513.82, "len": 9277, "voca": false, "cov": false}, {"id": "jjq9Pil1kYc", "t": "🔴明日はM3なので適当3Dピアノ配信します", "v": 12856, "d": 618.07, "len": 4346, "voca": false, "cov": false}, {"id": "RrgNaS-x6KM", "t": "🔴3Dパン屋で一人セッションする配信", "v": 12400, "d": 401.23, "len": 5368, "voca": false, "cov": false}, {"id": "jAnYmcG3gL4", "t": "🔴新しいシンセ音源買っﾎﾎﾎｗ【Serum2】", "v": 10867, "d": 461.94, "len": 15400, "voca": false, "cov": false}, {"id": "0KH0wt4oIsM", "t": "🔴新しいシンセ音源買っﾎﾎﾎｗ【Omnisphere3】", "v": 8485, "d": 256.93, "len": 17244, "voca": false, "cov": false}, {"id": "UyhvAVTzR-Q", "t": "🔴自分の曲のコード譜を書き起こす地味な配信", "v": 5305, "d": 67.05, "len": 9372, "voca": false, "cov": false}, {"id": "KnvePzuG3-A", "t": "🔴イベントの前日に設営完了する告知配信", "v": 5190, "d": 44.04, "len": 4367, "voca": false, "cov": false}, {"id": "z1duydhW6hw", "t": "🔴明日はM3なので適当3Dピアノ配信します", "v": 0, "d": 2113.23, "len": 0, "voca": false, "cov": false}]}