{"name": "𓂈", "updated": "2026-06-22", "fullFetched": "2026-06-22", "totalFetched": 59, "videos": [{"id": "KZVvx1iydwE", "t": "⠀", "v": 720379, "d": 444.05, "len": 147, "voca": true, "cov": false}, {"id": "NrFlUpmc9XI", "t": "⠀ ", "v": 77946, "d": 157.05, "len": 149, "voca": true, "cov": false}, {"id": "-05R1n7msW4", "t": "⠀", "v": 51062, "d": 367.05, "len": 162, "voca": true, "cov": false}, {"id": "hIHxapVsQ1E", "t": "⠀", "v": 50255, "d": 409.05, "len": 121, "voca": true, "cov": false}, {"id": "kIT1pfUo8bo", "t": "⠀", "v": 46592, "d": 262.05, "len": 159, "voca": true, "cov": false}, {"id": "bWt0kbHjNzI", "t": "⠀ ", "v": 45869, "d": 87.05, "len": 178, "voca": true, "cov": false}, {"id": "XBiDzpoZsa4", "t": "⠀ ", "v": 43478, "d": 45.05, "len": 138, "voca": true, "cov": false}, {"id": "vLzdUTH3n3I", "t": "僕だけ異常な訳じゃない #vocaloid #オリジナル曲 #初音ミク #hatsunemiku", "v": 39233, "d": 154.12, "len": 20, "voca": true, "cov": false}, {"id": "FjmTKhG-cyo", "t": "⠀ ", "v": 27525, "d": 220.05, "len": 138, "voca": true, "cov": false}, {"id": "xio7TxBgoTM", "t": "⠀", "v": 27109, "d": 492.07, "len": 110, "voca": true, "cov": false}, {"id": "vTmQ4QdFaGk", "t": "⠀", "v": 26360, "d": 535.07, "len": 81, "voca": true, "cov": false}, {"id": "CCJG8sc3jiQ", "t": "⠀ ", "v": 25826, "d": 325.05, "len": 166, "voca": true, "cov": false}, {"id": "1R3gfBnNXdU", "t": "不幸を願っている #vocaloid #ボカロ #オリジナル曲 #初音ミク", "v": 18400, "d": 101.12, "len": 20, "voca": true, "cov": false}, {"id": "3_T4JiExM7k", "t": "名前すら忘れたやつの #vocaloid #ボカロ #オリジナル曲 #初音ミク", "v": 15697, "d": 66.12, "len": 20, "voca": true, "cov": false}, {"id": "v2CM6IhXELQ", "t": "誰だって本心は #vocaloid #ボカロ #オリジナル曲 #初音ミク", "v": 14825, "d": 24.12, "len": 21, "voca": true, "cov": false}, {"id": "s-M1HeYgXnM", "t": "等身大の希望を持って #vocaloid #ボカロ #オリジナル曲 #初音ミク", "v": 14768, "d": 85.08, "len": 23, "voca": true, "cov": false}, {"id": "xhOrjzMUd6Y", "t": "失いたくない物は #vocaloid #ボカロ #オリジナル曲 #初音ミク", "v": 14679, "d": 43.14, "len": 15, "voca": true, "cov": false}, {"id": "HHvWcXqY9hM", "t": "かまってって #初音ミク #vocaloid #ボカロ", "v": 13990, "d": 122.1, "len": 22, "voca": true, "cov": false}, {"id": "_fYF168xwgE", "t": "誰もが皆エゴイスト #shorts #vocaloid", "v": 12668, "d": 355.12, "len": 21, "voca": true, "cov": false}, {"id": "FeE9E7zanJE", "t": "他人の不幸は #vocaloid #オリジナル曲 #初音ミク #hatsunemiku", "v": 12230, "d": 150.1, "len": 21, "voca": true, "cov": false}, {"id": "TvfWO5xFO6s", "t": "残酷な運命に #vocaloid #ボカロ #オリジナル曲 #初音ミク", "v": 11605, "d": 115.09, "len": 21, "voca": true, "cov": false}, {"id": "dtiqGUKbRLI", "t": "何で僕だけが #初音ミク #vocaloid #ボカロ", "v": 11074, "d": 129.1, "len": 18, "voca": true, "cov": false}, {"id": "xTcVOkXWvsA", "t": "愛や夢や願望とやらを #vocaloid #オリジナル曲 #初音ミク #hatsunemiku", "v": 9875, "d": 164.13, "len": 21, "voca": true, "cov": false}, {"id": "xUkvxx5il5k", "t": "ただ愛されたいよ #vocaloid #ボカロ #オリジナル曲 #初音ミク", "v": 9584, "d": 38.12, "len": 15, "voca": true, "cov": false}, {"id": "46y2BGSdQaw", "t": "過去に囚われて生きて #vocaloid #オリジナル曲 #初音ミク #hatsunemiku", "v": 9318, "d": 171.13, "len": 21, "voca": true, "cov": false}, {"id": "nCg9WCRy9Ak", "t": "愛されたいのに #VOCALOID #初音ミク #ボカロ", "v": 9145, "d": 346.14, "len": 23, "voca": true, "cov": false}, {"id": "94Vxt0nQSM4", "t": "全部知ってるよ #vocaloid #ボカロ #オリジナル曲 #初音ミク", "v": 9126, "d": 73.12, "len": 22, "voca": true, "cov": false}, {"id": "gMa1xTMRjS4", "t": "いつか見た女神のように #vocaloid #ボカロ #オリジナル曲 #初音ミク", "v": 8914, "d": 108.07, "len": 23, "voca": true, "cov": false}, {"id": "LmDi_SRgqGI", "t": "もう死にたいなんて嘘を #shorts #vocaloid", "v": 8595, "d": 363.13, "len": 23, "voca": true, "cov": false}, {"id": "sxs3KTnvg1Q", "t": "我儘な僕を #vocaloid #ボカロ #オリジナル曲 #初音ミク", "v": 8575, "d": 94.12, "len": 21, "voca": true, "cov": false}, {"id": "vTBVSjUWOy8", "t": "EGOIST / 初音ミク #vocaloid #オリジナル曲 #初音ミク", "v": 8558, "d": 268.09, "len": 20, "voca": true, "cov": false}, {"id": "09LOisFG_1o", "t": "君もそう思うよね #shorts #vocaloid", "v": 8507, "d": 311.14, "len": 23, "voca": true, "cov": false}, {"id": "D5q_x3sM4lg", "t": "君だけが欲しいの #初音ミク #vocaloid #ボカロ #オリジナル曲", "v": 8081, "d": 185.12, "len": 21, "voca": true, "cov": false}, {"id": "hGpQ5GUx4sY", "t": "どうしようも無いね #オリジナル曲 #初音ミク #vocaloid #shorts", "v": 7420, "d": 136.04, "len": 20, "voca": true, "cov": false}, {"id": "bYnxpf5OWLE", "t": "訳なく幸せにはなれないから #初音ミク #vocaloid #オリジナル曲", "v": 7313, "d": 199.12, "len": 22, "voca": true, "cov": false}, {"id": "Upg9_iQU2vk", "t": "満たされたいよ #vocaloid #ボカロ #オリジナル曲 #初音ミク", "v": 7132, "d": 31.03, "len": 15, "voca": true, "cov": false}, {"id": "RKEcazxR6C0", "t": "全部あいつのせいだ #オリジナル曲 #ボカロ #vocaloid #初音ミク #hatsunemiku", "v": 6998, "d": 490.16, "len": 15, "voca": true, "cov": false}, {"id": "F1QN8_g2fv0", "t": "人生のこたえあわせを #vocaloid #ボカロ #オリジナル曲 #初音ミク", "v": 6874, "d": 80.12, "len": 22, "voca": true, "cov": false}, {"id": "cViCkc7Xb1M", "t": "僕だけじゃない #vocaloid #オリジナル曲 #初音ミク #hatsunemiku", "v": 6813, "d": 143.12, "len": 21, "voca": true, "cov": false}, {"id": "qhBfECXuxY8", "t": "君の最期の言葉 #shorts #vocaloid", "v": 6407, "d": 217.13, "len": 29, "voca": true, "cov": false}, {"id": "KPSeyS7QQjU", "t": "この心に中身を #ボカロ #VOCALOID #music #hatsunemiku", "v": 6321, "d": 52.06, "len": 21, "voca": true, "cov": false}, {"id": "soXS0q34Ku8", "t": "思い出ばかりが #shorts #vocaloid", "v": 6315, "d": 206.1, "len": 21, "voca": true, "cov": false}, {"id": "KnZnZBYGOsY", "t": "まだ歌えるから #shorts #vocaloid", "v": 6071, "d": 291.09, "len": 23, "voca": true, "cov": false}, {"id": "cCPsLYeprpA", "t": "かつては皆持っていた感情だ #shorts #vocaloid", "v": 5573, "d": 321.14, "len": 21, "voca": true, "cov": false}, {"id": "D75w8Vf-NxA", "t": "あの歌姫のように #shorts #vocaloid", "v": 5565, "d": 234.12, "len": 22, "voca": true, "cov": false}, {"id": "cl4lRmNLAFA", "t": "まだ信じてた #ボカロ #VOCALOID #music #hatsunemiku", "v": 5411, "d": 59.06, "len": 22, "voca": true, "cov": false}, {"id": "_Ad0uM4WAu4", "t": "地獄のようで #shorts #vocaloid", "v": 5187, "d": 213.12, "len": 22, "voca": true, "cov": false}, {"id": "7vCm4trueyc", "t": "ただ見惚れてた #初音ミク #vocaloid #ボカロ #オリジナル曲", "v": 5112, "d": 177.14, "len": 27, "voca": true, "cov": false}, {"id": "YyTHnz7uoO4", "t": "君だけでいいから #shorts #vocaloid", "v": 5054, "d": 227.11, "len": 22, "voca": true, "cov": false}, {"id": "pOWKqlWKG28", "t": "なれるかな #初音ミク #vocaloid #オリジナル曲", "v": 4784, "d": 191.13, "len": 23, "voca": true, "cov": false}, {"id": "h63O3N9K3Fs", "t": "君によがって #VOCALOID #初音ミク #ボカロ", "v": 4770, "d": 338.09, "len": 22, "voca": true, "cov": false}, {"id": "bFl9ZgWK5aI", "t": "痛みも宝物 #初音ミク #hatsunemiku #music #オリジナル曲 #vocaloid #病み", "v": 4757, "d": 3.04, "len": 22, "voca": true, "cov": false}, {"id": "n5GJdUfoM4g", "t": "皆同じだって #shorts #vocaloid", "v": 4705, "d": 279.1, "len": 22, "voca": true, "cov": false}, {"id": "ZKgr1XI0fmk", "t": "KARAPPO / 初音ミク #vocaloid #オリジナル曲 #初音ミク", "v": 4634, "d": 258.12, "len": 23, "voca": true, "cov": false}, {"id": "hKjoOynnAN4", "t": "中身の無い言葉に価値は無いから #shorts #vocaloid", "v": 4561, "d": 301.1, "len": 23, "voca": true, "cov": false}, {"id": "H32g1vIOYnU", "t": "僕は何になりたいんだ #vocaloid #オリジナル曲 #初音ミク", "v": 4054, "d": 252.06, "len": 22, "voca": true, "cov": false}, {"id": "jFaeDQZQP1k", "t": "誰か探した #初音ミク #vocaloid #ボカロ", "v": 3827, "d": 10.05, "len": 14, "voca": true, "cov": false}, {"id": "WuSj1ipUg2o", "t": "それが自分だと #vocaloid #ボカロ #オリジナル曲 #初音ミク", "v": 3463, "d": 17.09, "len": 19, "voca": true, "cov": false}, {"id": "qW1IRSctTzA", "t": "Memory / 初音ミク #vocaloid #オリジナル曲 #初音ミク", "v": 3136, "d": 243.13, "len": 22, "voca": true, "cov": false}]}