{"name": "あめのむらくもP Official Channel", "updated": "2026-06-11", "fullFetched": "2026-06-11", "totalFetched": 26, "videos": [{"id": "akVa4UDbJUc", "t": "【GUMI】「他人事の音がする」　あめのむらくもP", "v": 1415674, "d": 3076.95, "len": 256, "voca": true}, {"id": "a7qHPM6gggk", "t": "【GUMI】「私、案山子。」　あめのむらくもＰ", "v": 764359, "d": 3028.86, "len": 193, "voca": true}, {"id": "4kBJaE3pXV0", "t": "【GUMI】エリカ　あめのむらくもＰ", "v": 664587, "d": 3103.76, "len": 226, "voca": true}, {"id": "O05W4trMf5k", "t": "【GUMI】「時の踊り子」　あめのむらくもＰ", "v": 618786, "d": 2909.85, "len": 181, "voca": true}, {"id": "ZeXPNJA0BYQ", "t": "【GUMI】「ビビッド」　あめのむらくもＰ", "v": 371378, "d": 2776.89, "len": 260, "voca": true}, {"id": "krG3ZOjGccc", "t": "【GUMI】「ネタソネピーポー」　あめのむらくもP", "v": 330879, "d": 2015.93, "len": 209, "voca": true}, {"id": "FCJno3ECU7w", "t": "【GUMI】「摩訶不思議」 あめのむらくもＰ", "v": 326573, "d": 2677.93, "len": 217, "voca": true}, {"id": "fTh8yL6MLoc", "t": "【GUMI】「雨ニ酔ウ」　あめのむらくもＰ", "v": 261859, "d": 2512.98, "len": 226, "voca": true}, {"id": "DUnLNwPNuzo", "t": "【Flower】「闇夜が僕らを呼んでいる」　あめのむらくもP", "v": 251464, "d": 1744.0, "len": 281, "voca": true}, {"id": "Xpu6D-XHHTk", "t": "【GUMI】「スキャットオノマトペ」　あめのむらくもＰ", "v": 244171, "d": 2536.94, "len": 182, "voca": true}, {"id": "d3ESssNDPgU", "t": "【flower】「RELOAD」　あめのむらくもP", "v": 243880, "d": 1937.98, "len": 188, "voca": true}, {"id": "kXXOyelj7Rc", "t": "【GUMI】「メメント」　あめのむらくもＰ", "v": 209525, "d": 2374.06, "len": 283, "voca": true}, {"id": "58wtes3emVI", "t": "【GUMI】「新時代のワルツ」　あめのむらくもＰ", "v": 175312, "d": 2482.98, "len": 189, "voca": true}, {"id": "oCN4Gzzzpvc", "t": "【Flower】「ロンリージャンキーダンス」　あめのむらくもP", "v": 119819, "d": 1368.93, "len": 242, "voca": true}, {"id": "JWYKa5vd7fQ", "t": "【初音ミク】「快晴を裂いて」　あめのむらくもP", "v": 85911, "d": 2070.99, "len": 248, "voca": true}, {"id": "W-bsGEsOdZQ", "t": "【初音ミク】「ゴーストモーション」　あめのむらくもP", "v": 84499, "d": 2102.98, "len": 206, "voca": true}, {"id": "5IYdEItDk0A", "t": "【flower】「ELLIE」　あめのむらくもP", "v": 83222, "d": 1803.98, "len": 306, "voca": true}, {"id": "8l5UUuPrWHQ", "t": "【GUMI】「φ」　あめのむらくもP", "v": 81148, "d": 1480.98, "len": 220, "voca": true}, {"id": "Hin6mMCfgjg", "t": "【GUMI】「ボクヲダマス」　あめのむらくもP", "v": 76658, "d": 1971.24, "len": 231, "voca": true}, {"id": "DPfstsa7E4M", "t": "【Flower】「狐狸変化」　あめのむらくもP", "v": 55592, "d": 1660.03, "len": 211, "voca": true}, {"id": "7G3WitIMHKc", "t": "【GUMI】「魔化不可避」　あめのむらくもP", "v": 49151, "d": 1261.02, "len": 208, "voca": true}, {"id": "asG8CDBrqRg", "t": "【知声】「GARBAGE」 あめのむらくもP", "v": 43639, "d": 1155.98, "len": 221, "voca": true}, {"id": "iH3l7jBHwlc", "t": "【知声】「花折ってうららか」　あめのむらくもP", "v": 30250, "d": 1083.98, "len": 234, "voca": true}, {"id": "ujOsdNJdZqM", "t": "【初音ミク】「はんぱもの」　あめのむらくもP", "v": 23138, "d": 1349.19, "len": 215, "voca": true}, {"id": "kFJHGBfC4CA", "t": "【あめのむらくもP】配信限定アルバム「底に花」　クロスフェード", "v": 8189, "d": 1042.02, "len": 633, "voca": false}, {"id": "lUK1n3k7AL0", "t": "12/28 新曲予告　#shorts", "v": 2610, "d": 1262.1, "len": 13, "voca": false}]}